chance_kafka-0.0.7.dist-info/METADATA
chance_kafka-0.0.7.dist-info/RECORD
chance_kafka-0.0.7.dist-info/WHEEL
chance_kafka-0.0.7.dist-info/top_level.txt
plantain/__init__.py
plantain/connections.py
plantain/constant.py
plantain/consumer.py
