Metadata-Version: 2.1
Name: chance-kafka
Version: 0.0.7
Summary: The kafka library for chancefocus
Home-page: https://gitee.com/QianFuFinancial/plantain.git
Author: Jimin Huang
Author-email: huangjimin@chancefocus.com
License: MIT
Platform: UNKNOWN
Requires-Dist: nose (>=1.3.7)
Requires-Dist: coverage (>=4.1)
Requires-Dist: chance-mock-logger (>=0.0.1)
Requires-Dist: flake8 (>=3.3.0)
Requires-Dist: arrow (>=0.12.0)
Requires-Dist: mock (>=2.0.0)
Requires-Dist: confluent-kafka (==1.1.0)
Requires-Dist: wheel (>=0.29.0)
